pymixer/__init__.py
pymixer/core.py
pymixer/midi.py
pymixer/project.py
pymixer/sound_makers.py
pymixer/wav.py
pymixer-0.2.0.dist-info/LICENSE
pymixer-0.2.0.dist-info/METADATA
pymixer-0.2.0.dist-info/WHEEL
pymixer-0.2.0.dist-info/top_level.txt
pymixer-0.2.0.dist-info/RECORD
