Metadata-Version: 2.1
Name: pymixer
Version: 0.2.0
Summary: A library for mixing input MIDI and/or WAV files to output WAV files.
Home-page: https://github.com/Nikolay-Lysenko/pymixer
Author: Nikolay Lysenko
Author-email: nikolay-lysenco@yandex.ru
License: MIT
Keywords: midi,mixing
Classifier: Development Status :: 4 - Beta
Classifier: Intended Audience :: Developers
Classifier: Topic :: Artistic Software
Classifier: License :: OSI Approved :: MIT License
Classifier: Programming Language :: Python :: 3
Requires-Python: >=3.10
License-File: LICENSE
Requires-Dist: numpy
Requires-Dist: pretty-midi
Requires-Dist: scipy
Requires-Dist: sinethesizer <0.7,>=0.6
